LICENSE
README.md
pyproject.toml
setup.cfg
src/retenmod/__init__.py
src/retenmod/model_funcs.py
src/retenmod.egg-info/PKG-INFO
src/retenmod.egg-info/SOURCES.txt
src/retenmod.egg-info/dependency_links.txt
src/retenmod.egg-info/requires.txt
src/retenmod.egg-info/top_level.txt