Metadata-Version: 2.1
Name: retenmod
Version: 0.0.1
Summary: retention models to forecast churn
Home-page: https://github.com/apwheele/retenmod
Author: Andrew Palmer Wheeler
Author-email: apwheele@gmail.com
License: UNKNOWN
Platform: UNKNOWN
Classifier: Programming Language :: Python :: 3
Classifier: License :: OSI Approved :: MIT License
Classifier: Operating System :: OS Independent
Classifier: Topic :: Scientific/Engineering :: Information Analysis
Requires-Python: >=3.6
License-File: LICENSE
